{
  "id": "contributing/docs-contribution",
  "title": "Contributing Documentation",
  "description": "Authoring standards",
  "source": "@site/docs/contributing/docs-contribution.md",
  "sourceDirName": "contributing",
  "slug": "/contributing/docs-contribution",
  "permalink": "/docs/contributing/docs-contribution",
  "draft": false,
  "unlisted": false,
  "tags": [],
  "version": "current",
  "frontMatter": {},
  "sidebar": "docsSidebar",
  "previous": {
    "title": "FAQ",
    "permalink": "/docs/faq"
  },
  "next": {
    "title": "Documentation Versioning Strategy",
    "permalink": "/docs/contributing/versioning-strategy"
  }
}